LICENSE
MANIFEST.in
README.rst
setup.py
simplepeg/__init__.py
simplepeg/exceptions.py
simplepeg/rd_parser.py
simplepeg/speg.py
simplepeg/speg_parser.py
simplepeg/speg_visitor.py
simplepeg.egg-info/PKG-INFO
simplepeg.egg-info/SOURCES.txt
simplepeg.egg-info/dependency_links.txt
simplepeg.egg-info/not-zip-safe
simplepeg.egg-info/top_level.txt