Metadata-Version: 1.1
Name: simplepeg
Version: 1.0.4
Summary: Python version of SimplePEG
Home-page: https://github.com/SimplePEG/Python
Author: Oleksii Okhrymenko
Author-email: ai_boy@live.ru
License: The MIT License (MIT)
